Workbook

Sheet README
A1: Family Income Statement 2026 — v4
A3: TABS:
A4: README — this guide
A5: Income Statement — main monthly P&L
A6: CC Detail — categorized variable spending (auto)
A7: Solar ROI — capital, monthly savings, payback
A8: Balances — month-end account snapshots
A9: Comp & Benefits — Matt 401k, Sue pension/403b, FSA tracking
A10: Scenarios — financial what-if analysis
A11: Charts — auto-generated charts (run from menu)
A12: Imports - Checking / Savings / Barclay — paste raw CSVs here
A13: Rules — merchant -> category mappings
... A91: Green number = positive / good variance

Sheet Income Statement
A1: Family Income Statement — 2026
A2: Yellow = enter values. White = formulas. Some lines pull from CC Detail or Solar ROI.
A4: Category | B4: Jan | C4: Feb | D4: Mar | E4: Apr | F4: May | G4: Jun | H4: Jul | I4: Aug | J4: Sep | K4: Oct | L4: Nov | M4: Dec | N4: YTD Total | O4: Avg/mo
A6: INCOME
A7: Sue — net pay (Town of Sharon) | B7: 6470.41 | C7: 6627.84 | D7: 6470.42 | E7: 9705.26 | F7: 6526.38 | N7: =SUM(B7:M7) | O7: =IFERROR(AVERAGEIF(B7:M7,"<>0"),0)
A8: Matt — net pay (MathWorks) | B8: 5179.07 | C8: 4551.25 | D8: 3827.99 | E8: 5427.48 | F8: 5989.44 | N8: =SUM(B8:M8) | O8: =IFERROR(AVERAGEIF(B8:M8,"<>0"),0)
A9: Q4 stakeholder bonus (MW lump, doubled) | N9: =SUM(B9:M9) | O9: =IFERROR(AVERAGEIF(B9:M9,"<>0"),0)
A10: Interest earned | B10: 155.3 | C10: 144.4 | D10: 87.26 | E10: 94.93 | F10: 79.5 | N10: =SUM(B10:M10) | O10: =IFERROR(AVERAGEIF(B10:M10,"<>0"),0)
A11: FSA Dep Care reimbursement (lump from Wex) | N11: =SUM(B11:M11) | O11: =IFERROR(AVERAGEIF(B11:M11,"<>0"),0)
A12: Tuition reimbursement (MathWorks) | N12: =SUM(B12:M12) | O12: =IFERROR(AVERAGEIF(B12:M12,"<>0"),0)
A13: Tax refunds (Federal/MA) | E13: 603 | N13: =SUM(B13:M13) | O13: =IFERROR(AVERAGEIF(B13:M13,"<>0"),0)
A14: CC rewards / Misc refunds / Side income | B14: 72.01 | C14: 77.53 | D14: 43.52 | E14: 209.21 | F14: 177.6 | G14: 90.95 | N14: =SUM(B14:M14) | O14: =IFERROR(AVERAGEIF(B14:M14,"<>0"),0)
A15: Total Income | B15: =SUM(B7:B14) | C15: =SUM(C7:C14) | D15: =SUM(D7:D14) | E15: =SUM(E7:E14) | F15: =SUM(F7:F14) | G15: =SUM(G7:G14) | H15: =SUM(H7:H14) | I15: =SUM(I7:I14) | ... N15: =SUM(N7:N14) | O15: =IFERROR(N15/COUNTIF(B15:M15,">0"),0)
A17: FIXED EXPENSES
A18: Mortgage (Rocket biweekly avg) | B18: 3288.58 | C18: 3288.58 | D18: 3288.58 | E18: 3288.58 | F18: 3288.58 | N18: =SUM(B18:M18) | O18: =IFERROR(AVERAGEIF(B18:M18,"<>0"),0)
A19: Car — 2023 Sienna loan (BoA) | B19: 384 | C19: 384 | D19: 576 | E19: 384 | F19: 384 | N19: =SUM(B19:M19) | O19: =IFERROR(AVERAGEIF(B19:M19,"<>0"),0)
A20: Car — 2022 RAV4 loan (Toyota) | B20: 416 | C20: 416 | D20: 624 | E20: 416 | F20: 416 | N20: =SUM(B20:M20) | O20: =IFERROR(AVERAGEIF(B20:M20,"<>0"),0)
A21: Childcare (checks) | B21: 724.6 | C21: 684.34 | E21: 1229.2 | F21: 421.6 | N21: =SUM(B21:M21) | O21: =IFERROR(AVERAGEIF(B21:M21,"<>0"),0)
A22: Tuition (Northeastern) | E22: 1848.3 | N22: =SUM(B22:M22) | O22: =IFERROR(AVERAGEIF(B22:M22,"<>0"),0)
A23: Life insurance — American General | B23: 46.19 | C23: 46.19 | D23: 46.19 | E23: 46.19 | F23: 46.19 | N23: =SUM(B23:M23) | O23: =IFERROR(AVERAGEIF(B23:M23,"<>0"),0)
A24: Life insurance — ALIC | C24: 90.39 | D24: 90.39 | E24: 90.39 | F24: 90.39 | N24: =SUM(B24:M24) | O24: =IFERROR(AVERAGEIF(B24:M24,"<>0"),0)
A25: Verizon | B25: 54.99 | C25: 54.99 | D25: 54.99 | E25: 54.99 | F25: 54.99 | N25: =SUM(B25:M25) | O25: =IFERROR(AVERAGEIF(B25:M25,"<>0"),0)
A26: T-Mobile | B26: 138.05 | C26: 139.64 | D26: 139.64 | E26: 139.61 | F26: 139.61 | N26: =SUM(B26:M26) | O26: =IFERROR(AVERAGEIF(B26:M26,"<>0"),0)
A27: Schwab investment (529) | B27: 100 | D27: 200 | E27: 100 | N27: =SUM(B27:M27) | O27: =IFERROR(AVERAGEIF(B27:M27,"<>0"),0)
A28: Fidelity investment ($50/mo) | B28: 100 | C28: 50 | D28: 200 | E28: 100 | G28: 100 | N28: =SUM(B28:M28) | O28: =IFERROR(AVERAGEIF(B28:M28,"<>0"),0)
A29: Total Fixed Expenses | B29: 50 | C29: 50 | D29: 50 | E29: 50 | F29: 50 | G29: 100 | H29: 0 | I29: 0 | J29: 0 | K29: 0 | L29: 0 | M29: 0 | N29: =SUM(N18:N28) | O29: =IFERROR(N29/COUNTIF(B29:M29,">0"),0)
A31: UTILITIES (Gas/Electric Currently Lumped)
A32: Gas bill | B32: 508.66 | C32: 528.66 | D32: 637 | E32: 405.83 | F32: 303.96 | G32: 223.28 | N32: =SUM(B32:M32) | O32: =IFERROR(AVERAGEIF(B32:M32,"<>0"),0)
A33: Electric (Eversource — pre-solar) | B33: 189.8 | C33: 364.31 | D33: 351.64 | E33: 207.68 | F33: 194.51 | G33: 87 | N33: =SUM(B33:M33) | O33: =IFERROR(AVERAGEIF(B33:M33,"<>0"),0)
A34: Water | N34: =SUM(B34:M34) | O34: =IFERROR(AVERAGEIF(B34:M34,"<>0"),0)
A35: Total Utilities | B35: =SUM(B32:B34) | C35: =SUM(C32:C34) | D35: =SUM(D32:D34) | E35: =SUM(E32:E34) | F35: =SUM(F32:F34) | G35: =SUM(G32:G34) | H35: =SUM(H32:H34) | I35: =SUM(I32:I34) | ... N35: =SUM(N32:N34) | O35: =IFERROR(N35/COUNTIF(B35:M35,">0"),0)
A37: VARIABLE SPENDING (auto-pulled from CC Detail)
A38: Groceries | B38: 635.4 | C38: 940.29 | D38: 701.42 | E38: 720.34 | F38: 427.34 | N38: =SUM(B38:M38) | O38: =IFERROR(AVERAGEIF(B38:M38,"<>0"),0)
A39: Gas / Vehicle | B39: 198.77 | C39: 242.84 | D39: 214.4 | E39: 356.42 | F39: 302.96 | N39: =SUM(B39:M39) | O39: =IFERROR(AVERAGEIF(B39:M39,"<>0"),0)
A40: Dining out | B40: 683.65 | C40: 884.87 | D40: 575 | E40: 1032.83 | F40: 427.35 | N40: =SUM(B40:M40) | O40: =IFERROR(AVERAGEIF(B40:M40,"<>0"),0)
A41: Subscriptions | B41: 111.05 | C41: 104.34 | D41: 111.05 | E41: 160.4 | F41: 153.07 | N41: =SUM(B41:M41) | O41: =IFERROR(AVERAGEIF(B41:M41,"<>0"),0)
A42: Kids / Activities | B42: 240 | C42: 27 | D42: 90 | E42: 490.32 | F42: 654.24 | N42: =SUM(B42:M42) | O42: =IFERROR(AVERAGEIF(B42:M42,"<>0"),0)
A43: Travel | D43: 30.54 | E43: 917.41 | F43: 104.8 | N43: =SUM(B43:M43) | O43: =IFERROR(AVERAGEIF(B43:M43,"<>0"),0)
A44: Personal Care | B44: 53.5 | C44: 1.44 | D44: 215.5 | E44: 96.53 | F44: 335.47 | N44: =SUM(B44:M44) | O44: =IFERROR(AVERAGEIF(B44:M44,"<>0"),0)
A45: Pharmacy / Health | B45: 35.54 | C45: 55.34 | D45: 18 | E45: 108.71 | F45: 8.72 | N45: =SUM(B45:M45) | O45: =IFERROR(AVERAGEIF(B45:M45,"<>0"),0)
A46: Home / Hardware | B46: 47.18 | C46: 186.05 | D46: 15.42 | E46: 224.72 | F46: 186.2 | N46: =SUM(B46:M46) | O46: =IFERROR(AVERAGEIF(B46:M46,"<>0"),0)
A47: Amazon (misc) | B47: 856.77 | C47: 267.06 | D47: 417.23 | E47: 482.16 | F47: 356.25 | N47: =SUM(B47:M47) | O47: =IFERROR(AVERAGEIF(B47:M47,"<>0"),0)
A48: Landscaping | E48: 490 | N48: =SUM(B48:M48) | O48: =IFERROR(AVERAGEIF(B48:M48,"<>0"),0)
A49: Cash / allowances | F49: 300 | N49: =SUM(B49:M49) | O49: =IFERROR(AVERAGEIF(B49:M49,"<>0"),0)
A50: Other / misc | B50: 2349.16 | C50: 461.55 | D50: 24417.03 | E50: 1839.2 | F50: 2000 | N50: =SUM(B50:M50) | O50: =IFERROR(AVERAGEIF(B50:M50,"<>0"),0)
A51: Total Variable Spending | B51: 5211.02 | C51: 3170.78 | D51: 26805.59 | E51: 6919.04 | F51: 5256.4 | G51: 0 | H51: 0 | I51: 0 | J51: 0 | K51: 0 | L51: 0 | M51: 0 | N51: =SUM(N38:N50) | O51: =IFERROR(N51/COUNTIF(B51:M51,">0"),0)
A53: ONE-TIME / LARGE ITEMS
A54: Solar install (capital — see Solar tab) | D54: 26318 | F54: 2000 | N54: =SUM(B54:M54) | O54: =IFERROR(N54/COUNTIF(B54:M54,">0"),0)
A55: Federal taxes owed (April) | E55: 3399.85 | N55: =SUM(B55:M55) | O55: =IFERROR(AVERAGEIF(B55:M55,"<>0"),0)
A56: TurboTax / tax prep | E56: 3399.85 | N56: =SUM(B56:M56) | O56: =IFERROR(AVERAGEIF(B56:M56,"<>0"),0)
A57: Other large item | N57: =SUM(B57:M57) | O57: =IFERROR(AVERAGEIF(B57:M57,"<>0"),0)
A58: Total One-Time | B58: =SUM(B54:B57) | C58: =SUM(C54:C57) | D58: =SUM(D54:D57) | E58: =SUM(E54:E57) | F58: =SUM(F54:F57) | G58: =SUM(G54:G57) | H58: =SUM(H54:H57) | I58: =SUM(I54:I57) | ... N58: =SUM(N54:N57) | O58: =IFERROR(N58/COUNTIF(B58:M58,">0"),0)
A60: TOTAL EXPENSES | B60: =B29+B35+B51+B58 | C60: =C29+C35+C51+C58 | D60: =D29+D35+D51+D58 | E60: =E29+E35+E51+E58 | F60: =F29+F35+F51+F58 | G60: =G29+G35+G51+G58 | H60: =H29+H35+H51+H58 | I60: =I29+I35+I51+I58 | ... N60: =N29+N35+N51+N58
A62: NET CASH FLOW (Income − Expenses) | B62: =B15-B60 | C62: =C15-C60 | D62: =D15-D60 | E62: =E15-E60 | F62: =F15-F60 | G62: =G15-G60 | H62: =H15-H60 | I62: =I15-I60 | ... N62: =N15-N60
A64: RECONCILIATION
A65: Checking — beginning balance | B65: 5223.93 | C65: =B68 | D65: =C68 | E65: =D68 | F65: =E68 | G65: =F68 | H65: =G68 | I65: =H68 | J65: =I68 | ... M65: =L68
A66: Predicted ending = beg + net cash flow | B66: =B65+B62 | C66: =C65+C62 | D66: =D65+D62 | E66: =E65+E62 | F66: =F65+F62 | G66: =G65+G62 | H66: =H65+H62 | I66: =I65+I62 | ... M66: =M65+M62
A67: Actual ending checking balance | B67: 4813 | C67: 4094 | D67: 6131 | E67: 6565 | F67: 6361
A68: Variance (actual − predicted) | B68: =B67-B66 | C68: =C67-C66 | D68: =D67-D66 | E68: =E67-E66 | F68: =F67-F66 | G68: =G67-G66 | H68: =H67-H66 | I68: =I67-I66 | ... M68: =M67-M66

Sheet CC Detail
A1: Variable Spending — by category (auto-populated)
A2: Auto-regenerated by Apps Script. Edit Rules tab to change categorization rather than typing here directly.
A4: Category | B4: Jan | C4: Feb | D4: Mar | E4: Apr | F4: May | G4: Jun | H4: Jul | I4: Aug | J4: Sep | K4: Oct | L4: Nov | M4: Dec | N4: YTD
A5: Groceries | B5: 635.4 | C5: 940.29 | D5: 701.42 | E5: 746.33 | F5: 630.8 | G5: 146.28 | N5: =SUM(B5:M5)
A6: Gas / Vehicle | B6: 198.77 | C6: 242.84 | D6: 214.4 | E6: 356.42 | F6: 530.1 | N6: =SUM(B6:M6)
A7: Dining out | B7: 683.65 | C7: 884.87 | D7: 575 | E7: 1032.83 | F7: 935.71 | G7: 74.96 | N7: =SUM(B7:M7)
A8: Subscriptions | B8: 111.05 | C8: 104.34 | D8: 111.05 | E8: 160.4 | F8: 154.06 | G8: 6.69 | N8: =SUM(B8:M8)
A9: Kids / Activities | B9: 240 | C9: 37.61 | D9: 128.26 | E9: 533.78 | F9: 677.24 | G9: 295.65 | N9: =SUM(B9:M9)
A10: Travel | D10: 30.54 | E10: 917.41 | F10: 104.8 | N10: =SUM(B10:M10)
A11: Personal Care | B11: 53.5 | C11: 1.44 | D11: 215.5 | E11: 96.53 | F11: 335.47 | G11: 100 | N11: =SUM(B11:M11)
A12: Pharmacy / Health | B12: 35.54 | C12: 55.34 | D12: 18 | E12: 108.71 | F12: 12.1 | G12: 3.79 | N12: =SUM(B12:M12)
A13: Home / Hardware | B13: 47.18 | C13: 186.05 | D13: 26.75 | E13: 224.72 | F13: 389.01 | G13: 123.82 | N13: =SUM(B13:M13)
A14: Amazon (misc) | B14: 856.77 | C14: 267.06 | D14: 417.23 | E14: 482.16 | F14: 688.51 | G14: 157.93 | N14: =SUM(B14:M14)
A15: Landscaping | E15: 490 | F15: 75 | G15: 65 | N15: =SUM(B15:M15)
A16: Cash / allowances | F16: 600 | N16: =SUM(B16:M16)
A17: Other / misc | B17: 2349.16 | C17: 450.94 | D17: 24367.44 | E17: 1769.75 | F17: 3985.28 | G17: -2.22 | N17: =SUM(B17:M17)
A18: Total variable spending | B18: =SUM(B5:B17) | C18: =SUM(C5:C17) | D18: =SUM(D5:D17) | E18: =SUM(E5:E17) | F18: =SUM(F5:F17) | G18: =SUM(G5:G17) | H18: =SUM(H5:H17) | I18: =SUM(I5:I17) | ... N18: =SUM(N5:N17)
A20: Barclaycard statement total (manual — sanity) | B20: 5863 | C20: 5466 | D20: 3914 | E20: 8658 | F20: 4911 | N20: =SUM(B20:M20)
A21: (Categorized − Statement) — should be ~0 | B21: =B18-B20 | C21: =C18-C20 | D21: =D18-D20 | E21: =E18-E20 | F21: =F18-F20 | G21: =G18-G20 | H21: =H18-H20 | I21: =I18-I20 | ... N21: =N18-N20

Sheet Solar ROI
A1: Solar Panel ROI Tracker
A2: Capital costs in row 5. Net meter goes live: track baseline (what you would have paid) vs. actual (with solar).
A4: Item | B4: Jan | C4: Feb | D4: Mar | E4: Apr | F4: May | G4: Jun | H4: Jul | I4: Aug | J4: Sep | K4: Oct | L4: Nov | M4: Dec | N4: YTD
A5: Capital outlay | B5: 5000 | D5: 26318 | F5: 2000 | N5: =SUM(B5:M5)
A6: Tax credits / incentives | N6: =SUM(B6:M6)
A7: Net capital cost | N7: =N5-N6
A9: Baseline electric (estimate) | N9: =SUM(B9:M9)
A10: Actual electric bill | F10: 87 | N10: =SUM(B10:M10)
A11: Monthly savings | B11: =B9-B10 | C11: =C9-C10 | D11: =D9-D10 | E11: =E9-E10 | F11: =F9-F10 | G11: =G9-G10 | H11: =H9-H10 | I11: =I9-I10 | ... M11: =M9-M10 | N11: =SUM(B11:M11)
A12: Cumulative savings | B12: =B11 | C12: =B12+C11 | D12: =C12+D11 | E12: =D12+E11 | F12: =E12+F11 | G12: =F12+G11 | H12: =G12+H11 | I12: =H12+I11 | J12: =I12+J11 | ... M12: =L12+M11
A14: Payback summary
A15: Net capital cost | B15: =N7
A16: Avg monthly savings | B16: =IFERROR(AVERAGEIF(B11:M11,"<>0"),0)
A17: Projected annual savings | B17: =B16*12
A18: Payback period (years) | B18: =IFERROR(B15/B17,"-")
A19: % paid back | B19: =IFERROR(N12/B15,0)
A21: ⚠ To make payback compute: (1) enter pre-solar baseline monthly bills in row 9 (orange). (2) Enter incentives in row 6 — NOTE: the 30% federal solar credit (25D) ended for systems placed in service after 12/31/2025 (OBBB, 7/4/2025); if yours went live in 2026 the federal credit is $0. MA still gives a 15% state credit up to $1,000. Full reinvestment model on the 'Solar Reinvestment' tab →

Sheet Balances
A1: Account Balances — month-end snapshots
A2: Snapshot at end of each month.
A4: Account | B4: Jan | C4: Feb | D4: Mar | E4: Apr | F4: May | G4: Jun | H4: Jul | I4: Aug | J4: Sep | K4: Oct | L4: Nov | M4: Dec
A5: Capital One Checking (7912)
A6: Capital One Savings (8940) | F6: 28188.03
A7: Capital One Venmo float (9345) | F7: 75 | G7: 26
A8: Fidelity Money Market | F8: 2929
A9: Schwab investment
A10: 529 | F10: 14298
A11: FSA Dep Care balance
A12: FSA Health Care balance
A13: Matt 401k (MathWorks) | F13: 228000
A14: Sue 403b (Equitable)
A15: Sue pension (estimated)
A16: Other
A17: Total assets | B17: =SUM(B5:B16) | C17: =SUM(C5:C16) | D17: =SUM(D5:D16) | E17: =SUM(E5:E16) | F17: =SUM(F5:F16) | G17: =SUM(G5:G16) | H17: =SUM(H5:H16) | I17: =SUM(I5:I16) | ... M17: =SUM(M5:M16)
A18: MoM change (assets) | C18: =IF(B17=0,0,C17-B17) | D18: =IF(C17=0,0,D17-C17) | E18: =IF(D17=0,0,E17-D17) | F18: =IF(E17=0,0,F17-E17) | G18: =IF(F17=0,0,G17-F17) | H18: =IF(G17=0,0,H17-G17) | I18: =IF(H17=0,0,I17-H17) | J18: =IF(I17=0,0,J17-I17) | ... M18: =IF(L17=0,0,M17-L17)

Sheet Comp & Benefits
A1: Compensation & Benefits Tracking
A2: Track YTD progress on retirement contributions, FSA, employer match. Update from paystubs (or from Workday/MathWorks portal monthly).
A4: MATT (MathWorks)
A5: Item | B5: Per pay period | C5: YTD | D5: Annual cap (2026) | E5: % used | F5: Notes
A6: Gross earnings | C6: 41980 | F6: Hourly + OT + Stakeholder + Reimbursements YTD
A7: Contribution rate % | B7: 0.23 | D7: 50% cap | F7: Auto-increases 1%/yr on May 1 up to 50% cap
A8: 401k contribution (target) | C8: 8794.41 | D8: 23500 | F8: 22% of ~$144k = ~$31,800 intended; PLAN AUTO-CAPS at $23,500. Maxes out by ~Sep.
A9: 401k match (3% baseline, throughout) | B9: 109.92 | C9: 1249.83 | D9: 4338 | F9: MW matches first 3% of pay; calculated as 3% of $144,612
A10: 401k match Q4 true-up (3% lump) | C10: 3164 | D10: 4338 | F10: MW typically doubles to 6% at year-end (lump in 401k acct, NOT cash)
A11: FSA Dep Care | B11: 153.85 | C11: 1538.5 | D11: 4000 | E11: =C11/D11 | F11: Reimbursed when receipts submitted
A12: FSA Health Care | B12: 96.15 | C12: 961.5 | D12: 3300 | E12: =C12/D12 | F12: 2026 limit; reimbursed for medical expenses
A13: Tuition reimbursement (received) | C13: 3634 | D13: 5250 | E13: =C13/D13 | F13: IRC §127 tax-free up to $5,250/yr
A14: Stakeholder Earnings YTD | C14: 2964.21 | F14: Doubled in Q4 — track when received
A15: Q4 stakeholder bonus | F15: Lump sum, hits checking separately
A17: SUE (Sharon Public Schools)
A18: Item | B18: Per pay period | C18: YTD | D18: Annual cap (2026) | E18: % used | F18: Notes
A19: MA pension contribution | F19: Mandatory deduction; not in retirement portfolio
A20: 403b contribution (Equitable) | B20: 0 | C20: 0 | D20: 23500 | E20: 0 | F20: STOPPED — high fees; consider restart + annual rollover to Fidelity
A21: 403b match | F21: Verify if district matches — depends on contract
A22: Total retirement % | F22: Track total Sue retirement savings rate including pension
A24: 529 (kids college)
A25: Item | B25: Per month | C25: YTD | D25: MA tax deduction cap | E25: % used | F25: Notes
A26: 529 contributions | B26: 100 | C26: =B26*5 | D26: 2000 | E26: =C26/D26 | F26: MA deducts up to $2k joint (~$100/yr tax savings)

Sheet Scenarios
A1: Financial Scenarios — what-if analysis
A2: Orange cells = inputs you can change. Other cells calculate automatically. Models 20-year horizon with simplified assumptions — not investment advice.
A4: ASSUMPTIONS
A5: Expected investment return (annual) | B5: 0.07 | C5: Stock/bond mix typical for retirement timeline
A6: Time horizon (years) | B6: 20
A7: MA marginal tax rate | B7: 0.05
A8: Federal marginal tax rate | B8: 0.22
A10: LOANS
A11: Loan | B11: Balance | C11: Rate | D11: Monthly pmt | E11: Months left | F11: Interest remaining
A12: RAV4 (Toyota) | B12: 0 | C12: 0 | D12: 0 | E12: 0 | F12: =D12*E12-B12
A13: Sienna (BoA) | B13: 14374 | C13: 0.0635 | D13: 384.16 | E13: 48 | F13: =D13*E13-B13
A14: Mortgage (Rocket) | B14: 350000 | C14: 0.0575 | D14: 3289 | E14: 320 | F14: =D14*E14-B14
A16: SCENARIOS — projected outcomes over horizon
A17: Action | B17: Status quo | C17: Restart Sue 403b at $300/mo | D17: Pay off RAV4 → backdoor Roth IRAs ($7k×2) | E17: Pay off RAV4 + restart Sue 403b | F17: Aggressive: all above + boost 529 to $300/mo
A18: Monthly cash impact (vs status quo) | B18: 0 | C18: =-300 | D18: =451-1167 | E18: =451-300 | F18: =451-1167-300-200
A19: New annual investment contributions | B19: 0 | C19: =300*12 | D19: =14000 | E19: =300*12 | F19: =300*12+14000+200*12
A20: Annual tax savings (federal+state) | B20: 0 | C20: =300*12*($B$8+$B$7) | D20: =0 | E20: =300*12*($B$8+$B$7) | F20: =300*12*($B$8+$B$7)+MIN(200*12,2000)*$B$7
A21: Loan interest saved (one-time) | B21: 0 | C21: =0 | D21: =F12 | E21: =F12 | F21: =F12
A22: Investment growth over horizon | B22: 0 | C22: =300*((((1+$B$5/12)^($B$6*12))-1)/($B$5/12)) | D22: =(14000/12)*((((1+$B$5/12)^($B$6*12))-1)/($B$5/12)) | E22: =300*((((1+$B$5/12)^($B$6*12))-1)/($B$5/12)) | F22: =(300+200)*((((1+$B$5/12)^($B$6*12))-1)/($B$5/12))+(14000/12)*((((1+$B$5/12)^($B$6*12))-1)/($B$5/12))
A23: TOTAL benefit (FV + interest saved + tax savings × horizon) | B23: =B22+B21+B20*$B$6 | C23: =C22+C21+C20*$B$6 | D23: =D22+D21+D20*$B$6 | E23: =E22+E21+E20*$B$6 | F23: =F22+F21+F20*$B$6

Sheet Charts
A1: Charts (auto-generated)
A2: Run: 📊 Family Finances → Generate / Refresh Charts. The Apps Script creates 4 charts on this tab from the data in Income Statement, CC Detail, Solar ROI, and Balances tabs.
A4: Cash Flow Summary (auto)
A5: Month | B5: Jan | C5: Feb | D5: Mar | E5: Apr | F5: May | G5: Jun | H5: Jul | I5: Aug | J5: Sep | K5: Oct | L5: Nov | M5: Dec
A6: Total Income | B6: ='Income Statement'!B15 | C6: ='Income Statement'!C15 | D6: ='Income Statement'!D15 | E6: ='Income Statement'!E15 | F6: ='Income Statement'!F15 | G6: ='Income Statement'!G15 | H6: ='Income Statement'!H15 | I6: ='Income Statement'!I15 | ... M6: ='Income Statement'!M15
A7: Total Expenses | B7: ='Income Statement'!B61 | C7: ='Income Statement'!C61 | D7: ='Income Statement'!D61 | E7: ='Income Statement'!E61 | F7: ='Income Statement'!F61 | G7: ='Income Statement'!G61 | H7: ='Income Statement'!H61 | I7: ='Income Statement'!I61 | ... M7: ='Income Statement'!M61
A8: Net Cash Flow | B8: ='Income Statement'!B63 | C8: ='Income Statement'!C63 | D8: ='Income Statement'!D63 | E8: ='Income Statement'!E63 | F8: ='Income Statement'!F63 | G8: ='Income Statement'!G63 | H8: ='Income Statement'!H63 | I8: ='Income Statement'!I63 | ... M8: ='Income Statement'!M63
A28: Solar Cumulative Savings vs. Capital
A29: Month | B29: Jan | C29: Feb | D29: Mar | E29: Apr | F29: May | G29: Jun | H29: Jul | I29: Aug | J29: Sep | K29: Oct | L29: Nov | M29: Dec
A30: Cumulative savings | B30: ='Solar ROI'!B12 | C30: ='Solar ROI'!C12 | D30: ='Solar ROI'!D12 | E30: ='Solar ROI'!E12 | F30: ='Solar ROI'!F12 | G30: ='Solar ROI'!G12 | H30: ='Solar ROI'!H12 | I30: ='Solar ROI'!I12 | ... M30: ='Solar ROI'!M12
A31: Net capital cost (reference) | B31: ='Solar ROI'!$N$7 | C31: ='Solar ROI'!$N$7 | D31: ='Solar ROI'!$N$7 | E31: ='Solar ROI'!$N$7 | F31: ='Solar ROI'!$N$7 | G31: ='Solar ROI'!$N$7 | H31: ='Solar ROI'!$N$7 | I31: ='Solar ROI'!$N$7 | ... M31: ='Solar ROI'!$N$7
A45: Total Assets Trend
A46: Month | B46: Jan | C46: Feb | D46: Mar | E46: Apr | F46: May | G46: Jun | H46: Jul | I46: Aug | J46: Sep | K46: Oct | L46: Nov | M46: Dec
A47: Total assets | B47: =Balances!B17 | C47: =Balances!C17 | D47: =Balances!D17 | E47: =Balances!E17 | F47: =Balances!F17 | G47: =Balances!G17 | H47: =Balances!H17 | I47: =Balances!I17 | ... M47: =Balances!M17

Sheet Imports - Checking
A1: Imports — Checking
A2: Paste Capital One Checking CSV here (full YTD recommended). Run: 📊 Family Finances → Categorize & Roll Up.
A4: Account Number | B4: Transaction Description | C4: Transaction Date | D4: Transaction Type | E4: Transaction Amount | F4: Balance | G4: → Category (auto)

Sheet Imports - Savings
A1: Imports — Savings
A2: Paste Capital One Savings CSV here.
A4: Account Number | B4: Transaction Description | C4: Transaction Date | D4: Transaction Type | E4: Transaction Amount | F4: Balance | G4: → Category (auto)

Sheet Imports - Barclay
A1: Imports — Barclay
A2: Paste Barclaycard CSV (skip header rows above 'Transaction Date').
A4: Transaction Date | B4: Description | C4: Category | D4: Amount | E4: Card Last 4 Digits | F4: Purchased by | G4: → Category (auto)

Sheet Rules
A1: Categorization Rules
A2: Edit to change merchant categorization. First match wins (top down).
A4: Pattern (regex) | B4: Category | C4: Notes
A5: Withdrawal to 360 Performance Savings | B5: __TRANSFER__ | C5: Move $ to savings
A6: Deposit from 360 Performance Savings | B6: __TRANSFER__ | C6: Move $ from savings
A7: Withdrawal to 360 Checking | B7: __TRANSFER__ | C7: Savings → Checking
A8: Deposit from 360 Checking | B8: __TRANSFER__ | C8: Checking → Savings
A9: BARCLAYCARD US CREDITCARD | B9: __TRANSFER__ | C9: Pay Barclaycard bill
A10: TARGET CARD SRVC PAYMENT | B10: __TRANSFER__ | C10: Pay Target card bill
A11: ^Payment Received$ | B11: __TRANSFER__ | C11: Barclaycard side of CC payment
A12: MATHWORKS INC PAYROLL | B12: __INCOME__:Matt | C12: Matt's paycheck
A13: TOWN OF SHARON PAYROLL | B13: __INCOME__:Sue | C13: Sue's paycheck
A14: COMM\. OF MASS\. MASTTAXRFD | B14: __INCOME__:Tax refunds | C14: MA tax refund
A15: Monthly Interest Paid | B15: __INCOME__:Interest | C15: Bank interest
... A20: ROCKET MORTGAGE | B20: __FIXED__:Mortgage | C20: Biweekly mortgage
A21: AMERICAN GEN LIF INS | B21: __FIXED__:Life ins (AmGen)
A22: ALIC INS PREM | B22: __FIXED__:Life ins (ALIC)
A23: TOYOTA ACH | B23: __FIXED__:Car (RAV4) | C23: RAV4 loan
A24: BANK OF AMERICA ONLINE PMT | B24: __FIXED__:Car (Sienna) | C24: Sienna auto loan
A25: VERIZON | B25: __FIXED__:Verizon | C25: Internet
A26: TMOBILE | B26: __FIXED__:T-Mobile | C26: Cell Phone
A27: EVERSOURCE | B27: __FIXED__:Electric
A28: SCHWAB ADV | B28: __FIXED__:Schwab investment
A29: FID BKG SVC | B29: __FIXED__:Fidelity investment
A30: NORTHEASTERN UNI | B30: __FIXED__:Tuition
A31: Check # | B31: __FIXED__:Childcare | C31: Most checks are childcare
A32: ALDI|TRADER JOE|BIG Y|STOP & SHOP|SHAWS|COSTCO WHSE|FARMER IN THE DELL|WARDS BERRY|FLANNEL COW|BUBBLING BROOK|WARD'S BERRY FARM | B32: Groceries
A33: COSTCO GAS|CUMBERLAND FARMS|SHELL OIL|EXXON|BJ.*FUEL|SUNOCO|ROJO CAR WASH|E-ZPASS|GULF OIL 92062891 | B33: Gas / Vehicle
A34: NETFLIX|PARAMOUNT|PEACOCK|NYTIMES|SPOTIFY|PATREON|MISSIONLOCAL|APPLE\.COM/BILL|Groupon|KIRO PRO | B34: Subscriptions
A35: WALPOLE YOUTH|RBI BASEBALL|HOCKOMOCK|PATRIOT FLAG|UNIVERSAL POWER|WALPOLE RECREA|NCAHS|OUTSIDERS MERCHAND|KOHR GOLF|FORE KICKS|SASSAMON TRACE|TOWNECRAFTERS|SP PARK STREET BOOKS | B35: Kids / Activities
A36: COURTYARD|MARRIOTT|SPOTHERO|CAPITOL EXPRESS|SMITH STORE|WIEHLE-RESTON|MR ICEO|PULSEWORKS|BINBOX|^METRO|MULTIPURE|DEERFIELD|LEVY@2NATIONAL|UBER *TRIP | B36: Travel
A37: DYNASTY BARBER|YOO NAILS|VIONIC SHOES|J CREW|NORDSTROM|On Sportswear|POSHMARK|SECOND GLANCE|FRANCISCO SILVA - HAIR|GREAT HAND REFLEXOLOGY | B37: Personal Care
A38: WALGREENS|CVS|PETCO|MUFFIN HOUSE|MUFFIN | B38: Pharmacy / Health
A39: HOME DEPOT|ROCKY.*HARDWARE|DOLLARTREE|HOBBY LOBBY|FIVE BELOW|WALMART|VEVOR|WOODCRAFT 335 | B39: Home / Hardware
A40: SULLIVAN LANDSCAPE | B40: Landscaping
A41: OPC\*US TREASURY|Intuit Inc | B41: __FIXED__:Federal taxes | C41: Annual tax payment
A42: TST\*|DD \*|SQ \*|TACO BELL|MCDONALD|WENDY|CHIPOTLE|DUNKIN|STARBUCKS|CAFE FRESH|PIZZERIA|ELEPHANT|MENCHIES|TESSIES|ANGELS CAFE|GINJO|SLICE\*|MONAHANS|RUSTIC GARDEN|RIBPUBLIC|CITIZEN CRUST|TACO AZUL|PHOBAMI|CHUCK E CHEESE|ESTELLA|EAGLE BROOK|PENANG|BEE SUITE|7-ELEVEN|BOSTON OPERA|YANKEE SPIRITS|TOTAL WINE|LS NORFOLK|CONVENIENCE FOOD|PANERA BREAD #203901 O | B42: Dining out
A43: AMZN|AMAZON | B43: Amazon (misc) | C43: Catch-all Amazon → reconcile on 'Amazon Reconciliation' tab
A44: ATM Withdrawal | B44: Cash / allowances

Sheet Pension - Sue
A1: Sue — MTRS Pension Calculator (Massachusetts Teachers' Retirement System)
A2: Membership Tier 1 confirmed — both 2003 and 2010 predate the 4/2/2012 Tier 2 cutoff. YELLOW = confirm in MyTRS • ORANGE = scenario inputs • Not affiliated with MTRS; verify against the official MTRS estimator before relying on any figure.
A4: ① CONFIRM IN MyTRS (mtrs.state.ma.us)
A5: Effective membership date (year) | B5: 2003 | C5: 2003 if funds left on account; 2010 if she took a refund & rejoined. Either way = Tier 1.
A6: Current creditable service (yrs, today) | B6: 16 | C6: ~16 if she refunded the 2003–07 years; ~20 if that service is still on account. MyTRS shows the exact figure.
A7: RetirementPlus participant? (Y/N) | B7: Y | C7: Auto-YES: joined post-7/1/2001 → mandatory R+ at 11%. A flat 11% on her paystub confirms it.
A8: Years as MTRS teacher (R+ 20-yr test) | B8: 16 | C8: Almost all her creditable service is teacher service; used only for the R+ 20-year test.
A10: ② SCENARIO INPUTS
A11: Sue's current age | B11: 45
A12: Current calendar year | B12: 2026
A13: Current annual salary ($) | B13: 85000 | C13: Enter Sue's actual salary.
A14: Expected annual raise (%) | B14: 0.02
A15: Planned retirement age (scenario) | B15: 60
A16: Buy-back: early years to restore | B16: 0 | C16: If she refunded 2003–07, she can repay to restore ~4–5 yrs. Try 4 to see the effect.
A18: ③ TIER 1 RULES (reference — do not edit) | E18: Age | F18: Factor
A19: Membership tier | B19: Tier 1 | E19: 55 | F19: 0.015
A20: Salary average period | B20: Highest 3 yrs | E20: 56 | F20: 0.016
A21: Maximum benefit cap | B21: 0.8 | E21: 57 | F21: 0.017
A22: R+ enhancement | B22: +2%/yr over 24 yrs | C22: Requires ≥30 yrs creditable, ≥20 as teacher, 11% for 5+ yrs. | E22: 58 | F22: 0.018
A23: Min retirement age (Tier 1) | B23: 55 | E23: 59 | F23: 0.019
E24: 60 | F24: 0.02
A25: ④ RESULT AT PLANNED RETIREMENT AGE | E25: 61 | F25: 0.021
A26: Creditable service at retirement | B26: =B6+(B15-B11)+B16 | E26: 62 | F26: 0.022
A27: Age factor at retirement | B27: =IF(B15<55,0,IF(B15>=65,0.025,0.015+(B15-55)*0.001)) | E27: 63 | F27: 0.023
A28: Salary average (3-yr, est.) $ | B28: =B13*((1+B14)^(B15-B11)+(1+B14)^(B15-B11-1)+(1+B14)^(B15-B11-2))/3 | E28: 64 | F28: 0.024
A29: Regular formula benefit % | B29: =MIN($B$21,B27*B26) | E29: 65 | F29: 0.025
A30: R+ eligible? | B30: =IF(AND($B$7="Y",B26>=30,B8+(B15-B11)>=20),"Yes","No")
A31: R+ formula benefit % | B31: =MIN($B$21,B27*B26+0.02*MAX(0,B26-24))
A32: Applied benefit % | B32: =IF(B30="Yes",B31,B29)
A33: ANNUAL PENSION ($) | B33: =B32*B28
A34: Monthly pension ($) | B34: =B33/12
A36: ⑤ PROJECTION BY RETIREMENT AGE (finds the earliest 80% cap)
A37: Retire age | B37: Year | C37: Cred. svc | D37: Age factor | E37: Regular % | F37: R+ elig? | G37: R+ % | H37: Applied % | I37: Annual pension $ | J37: 80% cap?
A38: 55 | B38: =$B$12+(A38-$B$11) | C38: =$B$6+(A38-$B$11)+$B$16 | D38: =IF(A38<55,0,IF(A38>=65,0.025,0.015+(A38-55)*0.001)) | E38: =MIN($B$21,D38*C38) | F38: =IF(AND($B$7="Y",C38>=30,$B$8+(A38-$B$11)>=20),"Y","N") | G38: =MIN($B$21,D38*C38+0.02*MAX(0,C38-24)) | H38: =IF(F38="Y",G38,E38) | I38: =H38*($B$13*((1+$B$14)^(A38-$B$11)+(1+$B$14)^(A38-$B$11-1)+(1+$B$14)^(A38-$B$11-2))/3) | J38: =IF(H38>=$B$21,"◄ 80% CAP","")
A39: 56 | B39: =$B$12+(A39-$B$11) | C39: =$B$6+(A39-$B$11)+$B$16 | D39: =IF(A39<55,0,IF(A39>=65,0.025,0.015+(A39-55)*0.001)) | E39: =MIN($B$21,D39*C39) | F39: =IF(AND($B$7="Y",C39>=30,$B$8+(A39-$B$11)>=20),"Y","N") | G39: =MIN($B$21,D39*C39+0.02*MAX(0,C39-24)) | H39: =IF(F39="Y",G39,E39) | I39: =H39*($B$13*((1+$B$14)^(A39-$B$11)+(1+$B$14)^(A39-$B$11-1)+(1+$B$14)^(A39-$B$11-2))/3) | J39: =IF(H39>=$B$21,"◄ 80% CAP","")
A40: 57 | B40: =$B$12+(A40-$B$11) | C40: =$B$6+(A40-$B$11)+$B$16 | D40: =IF(A40<55,0,IF(A40>=65,0.025,0.015+(A40-55)*0.001)) | E40: =MIN($B$21,D40*C40) | F40: =IF(AND($B$7="Y",C40>=30,$B$8+(A40-$B$11)>=20),"Y","N") | G40: =MIN($B$21,D40*C40+0.02*MAX(0,C40-24)) | H40: =IF(F40="Y",G40,E40) | I40: =H40*($B$13*((1+$B$14)^(A40-$B$11)+(1+$B$14)^(A40-$B$11-1)+(1+$B$14)^(A40-$B$11-2))/3) | J40: =IF(H40>=$B$21,"◄ 80% CAP","")
A41: 58 | B41: =$B$12+(A41-$B$11) | C41: =$B$6+(A41-$B$11)+$B$16 | D41: =IF(A41<55,0,IF(A41>=65,0.025,0.015+(A41-55)*0.001)) | E41: =MIN($B$21,D41*C41) | F41: =IF(AND($B$7="Y",C41>=30,$B$8+(A41-$B$11)>=20),"Y","N") | G41: =MIN($B$21,D41*C41+0.02*MAX(0,C41-24)) | H41: =IF(F41="Y",G41,E41) | I41: =H41*($B$13*((1+$B$14)^(A41-$B$11)+(1+$B$14)^(A41-$B$11-1)+(1+$B$14)^(A41-$B$11-2))/3) | J41: =IF(H41>=$B$21,"◄ 80% CAP","")
A42: 59 | B42: =$B$12+(A42-$B$11) | C42: =$B$6+(A42-$B$11)+$B$16 | D42: =IF(A42<55,0,IF(A42>=65,0.025,0.015+(A42-55)*0.001)) | E42: =MIN($B$21,D42*C42) | F42: =IF(AND($B$7="Y",C42>=30,$B$8+(A42-$B$11)>=20),"Y","N") | G42: =MIN($B$21,D42*C42+0.02*MAX(0,C42-24)) | H42: =IF(F42="Y",G42,E42) | I42: =H42*($B$13*((1+$B$14)^(A42-$B$11)+(1+$B$14)^(A42-$B$11-1)+(1+$B$14)^(A42-$B$11-2))/3) | J42: =IF(H42>=$B$21,"◄ 80% CAP","")
A43: 60 | B43: =$B$12+(A43-$B$11) | C43: =$B$6+(A43-$B$11)+$B$16 | D43: =IF(A43<55,0,IF(A43>=65,0.025,0.015+(A43-55)*0.001)) | E43: =MIN($B$21,D43*C43) | F43: =IF(AND($B$7="Y",C43>=30,$B$8+(A43-$B$11)>=20),"Y","N") | G43: =MIN($B$21,D43*C43+0.02*MAX(0,C43-24)) | H43: =IF(F43="Y",G43,E43) | I43: =H43*($B$13*((1+$B$14)^(A43-$B$11)+(1+$B$14)^(A43-$B$11-1)+(1+$B$14)^(A43-$B$11-2))/3) | J43: =IF(H43>=$B$21,"◄ 80% CAP","")
A44: 61 | B44: =$B$12+(A44-$B$11) | C44: =$B$6+(A44-$B$11)+$B$16 | D44: =IF(A44<55,0,IF(A44>=65,0.025,0.015+(A44-55)*0.001)) | E44: =MIN($B$21,D44*C44) | F44: =IF(AND($B$7="Y",C44>=30,$B$8+(A44-$B$11)>=20),"Y","N") | G44: =MIN($B$21,D44*C44+0.02*MAX(0,C44-24)) | H44: =IF(F44="Y",G44,E44) | I44: =H44*($B$13*((1+$B$14)^(A44-$B$11)+(1+$B$14)^(A44-$B$11-1)+(1+$B$14)^(A44-$B$11-2))/3) | J44: =IF(H44>=$B$21,"◄ 80% CAP","")
A45: 62 | B45: =$B$12+(A45-$B$11) | C45: =$B$6+(A45-$B$11)+$B$16 | D45: =IF(A45<55,0,IF(A45>=65,0.025,0.015+(A45-55)*0.001)) | E45: =MIN($B$21,D45*C45) | F45: =IF(AND($B$7="Y",C45>=30,$B$8+(A45-$B$11)>=20),"Y","N") | G45: =MIN($B$21,D45*C45+0.02*MAX(0,C45-24)) | H45: =IF(F45="Y",G45,E45) | I45: =H45*($B$13*((1+$B$14)^(A45-$B$11)+(1+$B$14)^(A45-$B$11-1)+(1+$B$14)^(A45-$B$11-2))/3) | J45: =IF(H45>=$B$21,"◄ 80% CAP","")
A46: 63 | B46: =$B$12+(A46-$B$11) | C46: =$B$6+(A46-$B$11)+$B$16 | D46: =IF(A46<55,0,IF(A46>=65,0.025,0.015+(A46-55)*0.001)) | E46: =MIN($B$21,D46*C46) | F46: =IF(AND($B$7="Y",C46>=30,$B$8+(A46-$B$11)>=20),"Y","N") | G46: =MIN($B$21,D46*C46+0.02*MAX(0,C46-24)) | H46: =IF(F46="Y",G46,E46) | I46: =H46*($B$13*((1+$B$14)^(A46-$B$11)+(1+$B$14)^(A46-$B$11-1)+(1+$B$14)^(A46-$B$11-2))/3) | J46: =IF(H46>=$B$21,"◄ 80% CAP","")
A47: 64 | B47: =$B$12+(A47-$B$11) | C47: =$B$6+(A47-$B$11)+$B$16 | D47: =IF(A47<55,0,IF(A47>=65,0.025,0.015+(A47-55)*0.001)) | E47: =MIN($B$21,D47*C47) | F47: =IF(AND($B$7="Y",C47>=30,$B$8+(A47-$B$11)>=20),"Y","N") | G47: =MIN($B$21,D47*C47+0.02*MAX(0,C47-24)) | H47: =IF(F47="Y",G47,E47) | I47: =H47*($B$13*((1+$B$14)^(A47-$B$11)+(1+$B$14)^(A47-$B$11-1)+(1+$B$14)^(A47-$B$11-2))/3) | J47: =IF(H47>=$B$21,"◄ 80% CAP","")
A48: 65 | B48: =$B$12+(A48-$B$11) | C48: =$B$6+(A48-$B$11)+$B$16 | D48: =IF(A48<55,0,IF(A48>=65,0.025,0.015+(A48-55)*0.001)) | E48: =MIN($B$21,D48*C48) | F48: =IF(AND($B$7="Y",C48>=30,$B$8+(A48-$B$11)>=20),"Y","N") | G48: =MIN($B$21,D48*C48+0.02*MAX(0,C48-24)) | H48: =IF(F48="Y",G48,E48) | I48: =H48*($B$13*((1+$B$14)^(A48-$B$11)+(1+$B$14)^(A48-$B$11-1)+(1+$B$14)^(A48-$B$11-2))/3) | J48: =IF(H48>=$B$21,"◄ 80% CAP","")
A49: 66 | B49: =$B$12+(A49-$B$11) | C49: =$B$6+(A49-$B$11)+$B$16 | D49: =IF(A49<55,0,IF(A49>=65,0.025,0.015+(A49-55)*0.001)) | E49: =MIN($B$21,D49*C49) | F49: =IF(AND($B$7="Y",C49>=30,$B$8+(A49-$B$11)>=20),"Y","N") | G49: =MIN($B$21,D49*C49+0.02*MAX(0,C49-24)) | H49: =IF(F49="Y",G49,E49) | I49: =H49*($B$13*((1+$B$14)^(A49-$B$11)+(1+$B$14)^(A49-$B$11-1)+(1+$B$14)^(A49-$B$11-2))/3) | J49: =IF(H49>=$B$21,"◄ 80% CAP","")
A50: 67 | B50: =$B$12+(A50-$B$11) | C50: =$B$6+(A50-$B$11)+$B$16 | D50: =IF(A50<55,0,IF(A50>=65,0.025,0.015+(A50-55)*0.001)) | E50: =MIN($B$21,D50*C50) | F50: =IF(AND($B$7="Y",C50>=30,$B$8+(A50-$B$11)>=20),"Y","N") | G50: =MIN($B$21,D50*C50+0.02*MAX(0,C50-24)) | H50: =IF(F50="Y",G50,E50) | I50: =H50*($B$13*((1+$B$14)^(A50-$B$11)+(1+$B$14)^(A50-$B$11-1)+(1+$B$14)^(A50-$B$11-2))/3) | J50: =IF(H50>=$B$21,"◄ 80% CAP","")
A52: Earliest age at 80% cap: | C52: =IFERROR(INDEX(A38:A50,MATCH(TRUE,INDEX(H38:H50>=$B$21,0),0)),"Not by 67")
A53: …in calendar year: | C53: =IFERROR($B$12+(C52-$B$11),"—")
A55: Note: salary average is a simple projection (current salary grown by the raise rate, averaged over the final 3 years). MTRS uses actual highest-3-consecutive-year earnings. R+ enhanced benefit only applies once she reaches 30 creditable years; otherwise the regular formula applies and R+ contributions are refunded.

Sheet FIRE Dashboard
A1: FIRE Dashboard — Naughton Family
A2: Educational planning tool, not investment advice. ORANGE = assumptions you set • YELLOW = balances/contributions (snapshot as of now — update over time). FI math uses a REAL (inflation-adjusted) return.
A4: ① HOUSEHOLD ASSUMPTIONS
A5: Matt's current age | B5: 45
A6: Sue's current age | B6: 45
A7: Current calendar year | B7: 2026
A8: Target annual retirement spend ($) | B8: 90000 | C8: Use your Income Statement expenses as a guide.
A9: Safe withdrawal rate (SWR) | B9: 0.04
A10: Nominal expected return | B10: 0.07 | C10: Matches the 7% on your Scenarios tab.
A11: Assumed inflation | B11: 0.03
A12: Real return (auto) | B12: =(1+B10)/(1+B11)-1
A14: ② CURRENT INVESTED ASSETS (from Balances)
A15: Matt 401k (MathWorks) | B15: 228000
A16: Sue 403b (Equitable) | B16: 0
A17: IRAs (Matt + Sue) | B17: 0
A18: HSA (invested portion) | B18: 0
A19: Taxable brokerage (Schwab) | B19: 0
A20: Cash earmarked for FI | B20: 0 | C20: Exclude your emergency fund.
A21: TOTAL INVESTED | B21: =SUM(B15:B20)
A22: (memo) 529 — excluded from FI | B22: 14298 | C22: Kids' college — not part of your FI number.
A24: ③ ANNUAL CONTRIBUTIONS
A25: Matt 401k (employee) | B25: 23500
A26: Employer 401k match | B26: 4338
A27: Sue 403b | B27: 0
A28: HSA | B28: 9000 | C28: 2027 family HSA limit.
A29: IRAs (both) | B29: 15000
A30: Taxable brokerage | B30: 0
A31: 529 | B31: 1200
A32: TOTAL ANNUAL INVESTED | B32: =SUM(B25:B31)
A34: ④ SAVINGS RATE
A35: Gross household income ($) | B35: 229000 | C35: Matt (~$144k) + Sue's salary.
A36: Savings rate | B36: =B32/B35
A38: ⑤ FI NUMBER (with & without the pension)
A39: Gross FI number (spend ÷ SWR) | B39: =B8/B9 | C39: Portfolio-only target, today's dollars — the conservative number to aim at.
A40: Sue's annual pension (from Pension tab) | B40: ='Pension - Sue'!B33 | C40: Future nominal $ (grown to her retirement) — treat the offset below as approximate.
A41: Social Security household (annual, est) | B41: 40000 | C41: WEP/GPO repealed (2025) — Sue keeps full spousal/survivor SS. Verify her record.
A42: Income floor (pension + SS) | B42: =B40+B41
A43: Pension+SS capitalized value | B43: =B42/B9 | C43: Roughly what that income floor is 'worth' vs a portfolio — it reduces the target below.
A44: NET FI number (target once floor starts) | B44: =MAX(0,(B8-B42)/B9) | C44: $0 means pension+SS alone cover target spend in the traditional-retirement phase.
A48: ⑥ YEARS TO FI (portfolio-only runway)
A49: Years to reach GROSS FI number | B49: =IFERROR(NPER(B12,-B32,-B21,B39),"check inputs") | C49: Current invested + annual contributions growing at the real return. Pension+SS shorten this once they begin (see ⑤).
A50: Matt's age at FI | B50: =IF(ISNUMBER(B49),B5+B49,"—")
A51: FI calendar year | B51: =IF(ISNUMBER(B49),B7+B49,"—")
A53: ⑦ PRE-59½ BRIDGE (early-access runway)
A54: Planned early-retire age (Matt) | B54: 55
A55: Roth IRA contributions (accessible) | B55: 0
A56: HSA receipt shoebox (accessible) | B56: 0
A57: Taxable brokerage | B57: 0
A58: Total accessible before 59½ | B58: =SUM(B55:B57)
A59: Years until 59½ | B59: =59.5-B54
A60: Annual spend uncovered in bridge ($) | B60: 90000 | C60: If Sue is still teaching, subtract her take-home — the gap may be small or zero.
A61: Bridge need | B61: =B59*B60
A62: Bridge surplus / (gap) | B62: =B58-B61
A64: ⑧ TWO-PHASE PLAN
A65: Phase 1 — Matt steps back first
A66: Sue keeps teaching: her salary + retiree-eligible health coverage bridge the household, so the portfolio keeps compounding and the pre-59½ gap above stays small.
A68: Phase 2 — Sue reaches her 80% pension cap
A69: =CONCATENATE("Sue hits the 80% cap at age ",'Pension - Sue'!C52," (year ",'Pension - Sue'!C53,"); ","both fully retired — the pension+SS floor then covers about ",TEXT(B42/B8,"0%")," of target spend.")

Sheet Amazon Reconciliation
A1: Amazon — Monthly Reconciliation
A2: All Amazon spend now lands in ONE bucket — 'Amazon (misc)', CC Detail row 14 — via a single regex rule (AMZN|AMAZON). Each month, split that total into real categories below. ORANGE = you enter $. The reference list at the bottom shows the actual Amazon transactions to guide the split.
A4: ① AMAZON TOTAL TO RECONCILE (auto — from CC Detail)
A5: Month | B5: Jan | C5: Feb | D5: Mar | E5: Apr | F5: May | G5: Jun | H5: Jul | I5: Aug | J5: Sep | K5: Oct | L5: Nov | M5: Dec | N5: YTD
A6: Amazon (misc) — to reconcile | B6: ='CC Detail'!B14 | C6: ='CC Detail'!C14 | D6: ='CC Detail'!D14 | E6: ='CC Detail'!E14 | F6: ='CC Detail'!F14 | G6: ='CC Detail'!G14 | H6: ='CC Detail'!H14 | I6: ='CC Detail'!I14 | ... M6: ='CC Detail'!M14 | N6: =SUM(B6:M6)
A8: ② ALLOCATE INTO CATEGORIES (enter $ per month)
A9: Category | B9: Jan | C9: Feb | D9: Mar | E9: Apr | F9: May | G9: Jun | H9: Jul | I9: Aug | J9: Sep | K9: Oct | L9: Nov | M9: Dec | N9: YTD
A10: Groceries | B10: 0 | C10: 0 | D10: 0 | E10: 0 | F10: 0 | G10: 0 | H10: 0 | I10: 0 | J10: 0 | K10: 0 | L10: 0 | M10: 0 | N10: =SUM(B10:M10)
A11: Kids / Activities | B11: 0 | C11: 0 | D11: 0 | E11: 0 | F11: 0 | G11: 0 | H11: 0 | I11: 0 | J11: 0 | K11: 0 | L11: 0 | M11: 0 | N11: =SUM(B11:M11)
A12: Personal Care | B12: 0 | C12: 0 | D12: 0 | E12: 0 | F12: 0 | G12: 0 | H12: 0 | I12: 0 | J12: 0 | K12: 0 | L12: 0 | M12: 0 | N12: =SUM(B12:M12)
A13: Pharmacy / Health | B13: 0 | C13: 0 | D13: 0 | E13: 0 | F13: 0 | G13: 0 | H13: 0 | I13: 0 | J13: 0 | K13: 0 | L13: 0 | M13: 0 | N13: =SUM(B13:M13)
A14: Home / Hardware | B14: 0 | C14: 0 | D14: 0 | E14: 0 | F14: 0 | G14: 0 | H14: 0 | I14: 0 | J14: 0 | K14: 0 | L14: 0 | M14: 0 | N14: =SUM(B14:M14)
A15: Subscriptions (Prime/Kindle/Audible) | B15: 0 | C15: 0 | D15: 0 | E15: 0 | F15: 0 | G15: 0 | H15: 0 | I15: 0 | J15: 0 | K15: 0 | L15: 0 | M15: 0 | N15: =SUM(B15:M15)
A16: Other / gifts | B16: 0 | C16: 0 | D16: 0 | E16: 0 | F16: 0 | G16: 0 | H16: 0 | I16: 0 | J16: 0 | K16: 0 | L16: 0 | M16: 0 | N16: =SUM(B16:M16)
A17: Allocated total | B17: =SUM(B10:B16) | C17: =SUM(C10:C16) | D17: =SUM(D10:D16) | E17: =SUM(E10:E16) | F17: =SUM(F10:F16) | G17: =SUM(G10:G16) | H17: =SUM(H10:H16) | I17: =SUM(I10:I16) | ... N17: =SUM(N10:N16)
A18: Unallocated remaining | B18: =B6-B17 | C18: =C6-C17 | D18: =D6-D17 | E18: =E6-E17 | F18: =F6-F17 | G18: =G6-G17 | H18: =H6-H17 | I18: =I6-I17 | ... N18: =N6-N17
A20: ③ RECONCILED CATEGORY TOTALS (YTD) — the un-muddied picture
A21: Category | B21: Native (CC Detail) | C21: + Amazon | D21: =True total (YTD)
A22: Groceries | B22: ='CC Detail'!N5 | C22: =N10 | D22: =B22+C22
A23: Kids / Activities | B23: ='CC Detail'!N9 | C23: =N11 | D23: =B23+C23
A24: Personal Care | B24: ='CC Detail'!N11 | C24: =N12 | D24: =B24+C24
A25: Pharmacy / Health | B25: ='CC Detail'!N12 | C25: =N13 | D25: =B25+C25
A26: Home / Hardware | B26: ='CC Detail'!N13 | C26: =N14 | D26: =B26+C26
A27: Subscriptions | B27: ='CC Detail'!N8 | C27: =N15 | D27: =B27+C27
A28: Other / gifts | B28: ='CC Detail'!N17 | C28: =N16 | D28: =B28+C28
A29: Note: once split, these 'true totals' show real spend per category — Amazon no longer hides hardware, hygiene, and kids' purchases in one lump. Feed these into the guardrail when it's built.
A32: ④ REFERENCE — current Amazon transactions (auto, read-only)
A33: Pulls Amazon rows from your Barclay import so you can see what to split. Refreshes when you paste new data.
A34: Date | B34: Description | C34: Amount | D34: Purchased by
A35: =IFERROR(FILTER({'Imports - Barclay'!A5:A,'Imports - Barclay'!B5:B,'Imports - Barclay'!D5:D,'Imports - Barclay'!F5:F},REGEXMATCH(UPPER('Imports - Barclay'!B5:B),"AMZN|AMAZON")),"No Amazon rows in current Barclay import")

Sheet Solar Reinvestment
A1: Solar — Reinvestment & Effective ROI
A2: Goal: redirect your former electric-bill spend into a growth vehicle so the solar's ROI compounds. ORANGE = inputs. Enphase has no CSV export, so enter the monthly energy log by hand (you can backfill Mar–Sep now, then add one row per month). Educational planning, not investment/tax advice.
A4: ① INCENTIVES & NET CAPITAL COST
A5: Gross capital outlay | B5: ='Solar ROI'!N5
A6: Federal ITC (25D) | B6: 0 | C6: $0 if placed in service in 2026 (OBBB ended 25D after 12/31/2025). If PTO by 12/31/2025, use ~0.30×gross.
A7: MA state credit (15%, max $1,000) | B7: =MIN(1000,0.15*B5)
A8: Other rebates / utility | B8: 0
A9: NET CAPITAL COST | B9: =B5-B6-B7-B8
A11: ② MONTHLY ENERGY LOG (Enphase — manual entry, kWh)
A12: Enter each month from your Enphase report. Net export = Exported − Imported (auto).
A13: Month | B13: Produced | C13: Consumed | D13: Imported | E13: Exported | F13: Net export
A14: Jan | F14: =E14-D14
A15: Feb | F15: =E15-D15
A16: Mar | F16: =E16-D16
A17: Apr | F17: =E17-D17
A18: May | F18: =E18-D18
A19: Jun | F19: =E19-D19
A20: Jul | F20: =E20-D20
A21: Aug | F21: =E21-D21
A22: Sep | F22: =E22-D22
A23: Oct | F23: =E23-D23
A24: Nov | F24: =E24-D24
A25: Dec | F25: =E25-D25
A26: Total | B26: =SUM(B14:B25) | C26: =SUM(C14:C25) | D26: =SUM(D14:D25) | E26: =SUM(E14:E25) | F26: =SUM(F14:F25)
A27: Latest Enphase snapshot (dashboard view): Produced 3.4 MWh · Consumed 2.6 MWh · Imported 1.3 MWh · Exported 2.2 MWh · Net exported ~872 kWh · Solar offset 134%. Replace with monthly report values above.
A30: ③ SAVINGS TO REINVEST
A31: Pre-solar baseline bill ($/mo) | B31: 300 | C31: What you used to pay — this is the money you're freeing up.
A32: Post-solar actual bill ($/mo) | B32: 10 | C32: Fixed customer/connection charges that remain.
A33: Monthly avoided cost (reinvest) | B33: =MAX(0,B31-B32)
A34: Annual avoided cost | B34: =B33*12
A35: SMART incentive ($/kWh) | B35: 0.03
A36: Est. annual production (kWh) | B36: 11000
A37: Annual SMART payment (yrs 1–10) | B37: =B35*B36
A38: Blended electric rate ($/kWh) | B38: 0.3 | C38: Used to value net-metering credits from exports.
A40: ④ REINVESTMENT MODEL — accelerate the ROI
A41: Reinvestment return (nominal) | B41: 0.07 | C41: Matches the 7% on your Scenarios tab.
A42: Electric rate escalation (%/yr) | B42: 0.04
A43: Horizon (years) | B43: 25
A44: First full year | B44: 2026
A46: Year | B46: Calendar | C46: Avoided cost | D46: SMART | E46: Reinvested/yr | F46: Reinvested bal. | G46: Simple cum. | H46: Status
A47: 1 | B47: =$B$44+(A47-1) | C47: =$B$34*(1+$B$42)^(A47-1) | D47: =IF(A47<=10,$B$37,0) | E47: =C47+D47 | F47: =E47 | G47: =E47 | H47: =IF(F47>=$B$9,"◄ accelerated payback",IF(G47>=$B$9,"simple payback",""))
A48: 2 | B48: =$B$44+(A48-1) | C48: =$B$34*(1+$B$42)^(A48-1) | D48: =IF(A48<=10,$B$37,0) | E48: =C48+D48 | F48: =F47*(1+$B$41)+E48 | G48: =G47+E48 | H48: =IF(F48>=$B$9,"◄ accelerated payback",IF(G48>=$B$9,"simple payback",""))
A49: 3 | B49: =$B$44+(A49-1) | C49: =$B$34*(1+$B$42)^(A49-1) | D49: =IF(A49<=10,$B$37,0) | E49: =C49+D49 | F49: =F48*(1+$B$41)+E49 | G49: =G48+E49 | H49: =IF(F49>=$B$9,"◄ accelerated payback",IF(G49>=$B$9,"simple payback",""))
A50: 4 | B50: =$B$44+(A50-1) | C50: =$B$34*(1+$B$42)^(A50-1) | D50: =IF(A50<=10,$B$37,0) | E50: =C50+D50 | F50: =F49*(1+$B$41)+E50 | G50: =G49+E50 | H50: =IF(F50>=$B$9,"◄ accelerated payback",IF(G50>=$B$9,"simple payback",""))
A51: 5 | B51: =$B$44+(A51-1) | C51: =$B$34*(1+$B$42)^(A51-1) | D51: =IF(A51<=10,$B$37,0) | E51: =C51+D51 | F51: =F50*(1+$B$41)+E51 | G51: =G50+E51 | H51: =IF(F51>=$B$9,"◄ accelerated payback",IF(G51>=$B$9,"simple payback",""))
A52: 6 | B52: =$B$44+(A52-1) | C52: =$B$34*(1+$B$42)^(A52-1) | D52: =IF(A52<=10,$B$37,0) | E52: =C52+D52 | F52: =F51*(1+$B$41)+E52 | G52: =G51+E52 | H52: =IF(F52>=$B$9,"◄ accelerated payback",IF(G52>=$B$9,"simple payback",""))
A53: 7 | B53: =$B$44+(A53-1) | C53: =$B$34*(1+$B$42)^(A53-1) | D53: =IF(A53<=10,$B$37,0) | E53: =C53+D53 | F53: =F52*(1+$B$41)+E53 | G53: =G52+E53 | H53: =IF(F53>=$B$9,"◄ accelerated payback",IF(G53>=$B$9,"simple payback",""))
A54: 8 | B54: =$B$44+(A54-1) | C54: =$B$34*(1+$B$42)^(A54-1) | D54: =IF(A54<=10,$B$37,0) | E54: =C54+D54 | F54: =F53*(1+$B$41)+E54 | G54: =G53+E54 | H54: =IF(F54>=$B$9,"◄ accelerated payback",IF(G54>=$B$9,"simple payback",""))
A55: 9 | B55: =$B$44+(A55-1) | C55: =$B$34*(1+$B$42)^(A55-1) | D55: =IF(A55<=10,$B$37,0) | E55: =C55+D55 | F55: =F54*(1+$B$41)+E55 | G55: =G54+E55 | H55: =IF(F55>=$B$9,"◄ accelerated payback",IF(G55>=$B$9,"simple payback",""))
A56: 10 | B56: =$B$44+(A56-1) | C56: =$B$34*(1+$B$42)^(A56-1) | D56: =IF(A56<=10,$B$37,0) | E56: =C56+D56 | F56: =F55*(1+$B$41)+E56 | G56: =G55+E56 | H56: =IF(F56>=$B$9,"◄ accelerated payback",IF(G56>=$B$9,"simple payback",""))
A57: 11 | B57: =$B$44+(A57-1) | C57: =$B$34*(1+$B$42)^(A57-1) | D57: =IF(A57<=10,$B$37,0) | E57: =C57+D57 | F57: =F56*(1+$B$41)+E57 | G57: =G56+E57 | H57: =IF(F57>=$B$9,"◄ accelerated payback",IF(G57>=$B$9,"simple payback",""))
A58: 12 | B58: =$B$44+(A58-1) | C58: =$B$34*(1+$B$42)^(A58-1) | D58: =IF(A58<=10,$B$37,0) | E58: =C58+D58 | F58: =F57*(1+$B$41)+E58 | G58: =G57+E58 | H58: =IF(F58>=$B$9,"◄ accelerated payback",IF(G58>=$B$9,"simple payback",""))
A59: 13 | B59: =$B$44+(A59-1) | C59: =$B$34*(1+$B$42)^(A59-1) | D59: =IF(A59<=10,$B$37,0) | E59: =C59+D59 | F59: =F58*(1+$B$41)+E59 | G59: =G58+E59 | H59: =IF(F59>=$B$9,"◄ accelerated payback",IF(G59>=$B$9,"simple payback",""))
... A71: 25 | B71: =$B$44+(A71-1) | C71: =$B$34*(1+$B$42)^(A71-1) | D71: =IF(A71<=10,$B$37,0) | E71: =C71+D71 | F71: =F70*(1+$B$41)+E71 | G71: =G70+E71 | H71: =IF(F71>=$B$9,"◄ accelerated payback",IF(G71>=$B$9,"simple payback",""))
A73: Simple payback (year #): | C73: =IFERROR(INDEX(A47:A71,MATCH(TRUE,INDEX(G47:G71>=$B$9,0),0)),">25")
A74: Accelerated payback (year #): | C74: =IFERROR(INDEX(A47:A71,MATCH(TRUE,INDEX(F47:F71>=$B$9,0),0)),">25")
A75: Reinvested value at horizon: | C75: =INDEX(F47:F71,MATCH($B$43,A47:A71,0))
A76: Net gain (value − net capital): | C76: =C75-B9
A78: Takeaway: 'Simple payback' is when avoided bills alone repay the system. 'Accelerated payback' is when those same dollars — invested at your return — repay it. The gap between them, and the horizon value above, is the compounding you unlock by reinvesting instead of just banking lower bills. Add the monthly avoided cost (B33) to the FIRE Dashboard contributions to fold it into your savings rate.

Sheet HSA Election Planner
A1: HSA Election Planner — November open enrollment
A2: Turns your freed-up cash (solar + mobile + old FSA) into a concrete HSA election for the 2027 plan year. ORANGE = inputs. Educational planning, not tax advice.
A4: ① 2027 HSA LIMIT
A5: Coverage type | B5: Family
A6: 2027 HSA limit (family) | B6: 9000 | C6: Self-only 2027 = $4,500. Family = $9,000.
A7: Catch-up (age 55+, each) | B7: 0 | C7: You're 45 — the +$1,000 each starts in 2036.
A8: Employer HSA seed/contribution | B8: 0 | C8: If MathWorks seeds the HSA, it counts against the limit — enter it.
A9: Your max employee election | B9: =B6+B7-B8
A10: Pay periods / year | B10: 26 | C10: MathWorks is biweekly = 26.
A11: Max per paycheck | B11: =B9/B10
A13: ② FREED-UP CASH TO REDIRECT (annual)
A14: Solar avoided cost (from Solar tab) | B14: ='Solar Reinvestment'!B34
A15: Mobile / phone savings | B15: 600 | C15: From switching to the cheaper carrier.
A16: Former FSA Health Care contribution | B16: 2500 | C16: What you were putting in the FSA (~$96/pay × 26). This moves to the HSA.
A17: Other freed cash | B17: 0
A18: TOTAL new annual money | B18: =SUM(B14:B17)
A20: ③ ELECTION PLAN
A21: Suggested election (fund HSA from freed cash) | B21: =MIN(B9,B18) | C21: Fund the more tax-efficient HSA first, up to the limit.
A22: Your chosen HSA election | B22: =B21 | C22: Override with the number you actually elect.
A23: → Per paycheck | B23: =B22/B10
A24: → % of family limit used | B24: =B22/B6
A25: Remaining freed cash → IRAs | B25: =MAX(0,B18-B22)
A26: Extra needed to hit $9,000 max | B26: =MAX(0,B9-B18) | C26: Shortfall between freed cash and a full max — pull from elsewhere if you want to top out.
A28: ④ DECISION NOTES (from our planning)
A29: • HSA is the most tax-efficient bucket (triple advantage + the payroll-tax break) — fund it first from freed cash, then overflow to IRAs.
A30: • Orthodontia: pay out of pocket, save every receipt, let the HSA stay invested and reimburse yourself later (the 'shoebox' growth play).
A31: • Open + fund the HSA (even $1) BEFORE the first ortho expense — expenses incurred before the account exists can never be reimbursed.
A32: • Confirm your 2026 FSA has no carryover/grace period bleeding into 2027 — it can block HSA eligibility early in the year. Consider a limited-purpose (dental/vision) FSA.
A33: • 2027 IRA limit isn't official yet (~$7,500 each expected); confirm in November before finalizing the IRA split.

Sheet Monthly Entry
A1: Monthly Entry — one place to update everything
A2: Pick the month, fill in what you have (blanks are skipped), then run 📊 Family Finances → Post Monthly Entry. Values fan out to Balances, Solar, Amazon Reconciliation and Comp & Benefits. You can also fill this from your phone via the linked Google Form.
A4: Month to post | B4: Sep | C4: Choose the month these figures belong to.
A5: Data as of (date) | C5: Optional — for your records.
A6: ① ACCOUNT BALANCES (month-end)
A7: Capital One Checking | C7: → Balances
A8: Capital One Savings
A9: Venmo float
A10: Fidelity Money Market
A11: Schwab investment
A12: 529
A13: FSA Dep Care balance
A14: FSA Health Care balance
A15: Matt 401k
A16: Sue 403b
A17: Sue pension (est.)
A18: Other
A20: ② SOLAR — ENERGY (Enphase, kWh)
A21: Produced (kWh) | C21: → Solar Reinvestment log
A22: Consumed (kWh)
A23: Imported (kWh)
A24: Exported (kWh)
A25: ③ SOLAR — ELECTRIC BILL
A26: Baseline electric (would-have-paid) | C26: → Solar ROI row 9
A27: Actual electric bill | C27: → Solar ROI row 10
A29: ④ AMAZON — split this month's total into buckets
A30: Amazon total to split (auto) | B30: =IFERROR(INDEX('CC Detail'!B14:M14,MATCH($B$4,{"Jan","Feb","Mar","Apr","May","Jun","Jul","Aug","Sep","Oct","Nov","Dec"},0)),"") | C30: Pulled from CC Detail for the chosen month — split it below.
A31: Groceries | C31: → Amazon Reconciliation
A32: Kids / Activities
A33: Personal Care
A34: Pharmacy / Health
A35: Home / Hardware
A36: Subscriptions
A37: Other / gifts
A38: Split check (should match total) | B38: =SUM(B31:B37) | C38: Compare to Amazon total above.
A40: ⑤ COMP & BENEFITS (YTD, from paystub)
A41: Matt gross earnings YTD | C41: → Comp & Benefits
A42: Matt 401k contribution YTD
A43: Matt 401k match YTD
A44: FSA Dep Care YTD
A45: FSA Health Care YTD
A46: Tuition reimbursement YTD
A47: Stakeholder earnings YTD
A48: Sue 403b YTD
A49: 529 contributions YTD
A51: After posting, blank the input cells for next month (or use the Form). The script only writes fields you filled, into the month you chose above.
